pyforestscan/__init__.py
pyforestscan/calculate.py
pyforestscan/filters.py
pyforestscan/handlers.py
pyforestscan/pipeline.py
pyforestscan/process.py
pyforestscan/utils.py
pyforestscan/visualize.py
pyforestscan-0.3.7.dist-info/licenses/LICENSE
tests/__init__.py
tests/test_calculate.py
tests/test_filters.py
tests/test_handlers.py
tests/test_process.py
tests/test_utils.py
pyforestscan-0.3.7.dist-info/METADATA
pyforestscan-0.3.7.dist-info/WHEEL
pyforestscan-0.3.7.dist-info/top_level.txt
pyforestscan-0.3.7.dist-info/RECORD
