Metadata-Version: 2.4
Name: pyforestscan
Version: 0.3.7
Summary: Analyzing forest structure using aerial LiDAR data
Home-page: https://github.com/iosefa/PyForestScan
Author: Joseph Emile Honour Percival
Author-email: ipercival@gmail.com
Project-URL: Bug Tracker, https://github.com/iosefa/PyForestScan/issues
Classifier: Programming Language :: Python :: 3
Classifier: License :: OSI Approved :: MIT License
Classifier: Operating System :: OS Independent
Requires-Python: >=3.11
License-File: LICENSE
Requires-Dist: requests>=2.32.4
Requires-Dist: rasterio>=1.3.11
Requires-Dist: pdal>=3.4.5
Requires-Dist: geopandas>=1.1.1
Requires-Dist: pyproj>=3.7.1
Requires-Dist: shapely>=2.1.1
Requires-Dist: pandas>=2.3.0
Requires-Dist: numpy>=2.3.1
Requires-Dist: matplotlib>=3.10.3
Requires-Dist: scipy>=1.16.0
Provides-Extra: dev
Requires-Dist: pytest>=7.0.0; extra == "dev"
Requires-Dist: pytest-cov>=4.0.0; extra == "dev"
Requires-Dist: flake8>=6.0.0; extra == "dev"
Requires-Dist: black>=23.0.0; extra == "dev"
Dynamic: author
Dynamic: author-email
Dynamic: classifier
Dynamic: description
Dynamic: description-content-type
Dynamic: home-page
Dynamic: license-file
Dynamic: project-url
Dynamic: provides-extra
Dynamic: requires-dist
Dynamic: requires-python
Dynamic: summary
